package_name/__init__.py
normative-0.0.1.dist-info/LICENSE.txt
normative-0.0.1.dist-info/METADATA
normative-0.0.1.dist-info/WHEEL
normative-0.0.1.dist-info/top_level.txt
normative-0.0.1.dist-info/RECORD
